sqlmigrately/__init__.py
sqlmigrately/exceptions.py
sqlmigrately/main.py
sqlmigrately/types.py
sqlmigrately/utils.py
SQLMigrately-0.1.2.dist-info/LICENSE
SQLMigrately-0.1.2.dist-info/METADATA
SQLMigrately-0.1.2.dist-info/WHEEL
SQLMigrately-0.1.2.dist-info/top_level.txt
SQLMigrately-0.1.2.dist-info/RECORD
