Metadata-Version: 2.1
Name: SQLMigrately
Version: 0.1.2
Summary: Zero setup SQL schema migration from pandas DataFrames
Author-email: blacksuan19 <py@blacksuan19.dev>
Classifier: Programming Language :: Python
Classifier: Programming Language :: Python :: 3
Requires-Python: >=3.10
License-File: LICENSE
Requires-Dist: pandas
Requires-Dist: sqlalchemy
Requires-Dist: loguru
Provides-Extra: dev
Requires-Dist: black; extra == "dev"
Requires-Dist: bumpver; extra == "dev"
Requires-Dist: pip-tools; extra == "dev"
Requires-Dist: wheel; extra == "dev"
